{"orbit": 8, "Type": 21, "deg": "8", "tup": [35, 53, 150, 493, 517], "str_rep": "1 2 2 3 3\n 1 2 2 3 3\n 1 2 4 5 3\n 1 1 4 5 5\n 4 4 4 5 5", "html_rep": "<span style=\"color:#73C6B6\">&#9724;</span> <span style=\"color:#F4D03F\">&#9724;</span> <span style=\"color:#F4D03F\">&#9724;</span> <span style=\"color:#CD6155\">&#9724;</span> <span style=\"color:#CD6155\">&#9724;</span><br/> <span style=\"color:#73C6B6\">&#9724;</span> <span style=\"color:#F4D03F\">&#9724;</span> <span style=\"color:#F4D03F\">&#9724;</span> <span style=\"color:#CD6155\">&#9724;</span> <span style=\"color:#CD6155\">&#9724;</span><br/> <span style=\"color:#73C6B6\">&#9724;</span> <span style=\"color:#F4D03F\">&#9724;</span> <span style=\"color:#A569BD\">&#9724;</span> <span style=\"color:#4682B4\">&#9724;</span> <span style=\"color:#CD6155\">&#9724;</span><br/> <span style=\"color:#73C6B6\">&#9724;</span> <span style=\"color:#73C6B6\">&#9724;</span> <span style=\"color:#A569BD\">&#9724;</span> <span style=\"color:#4682B4\">&#9724;</span> <span style=\"color:#4682B4\">&#9724;</span><br/> <span style=\"color:#A569BD\">&#9724;</span> <span style=\"color:#A569BD\">&#9724;</span> <span style=\"color:#A569BD\">&#9724;</span> <span style=\"color:#4682B4\">&#9724;</span> <span style=\"color:#4682B4\">&#9724;</span>", "name": 2374, "id": 0, "children": [{"orbit": 8, "Type": 395, "deg": "6", "tup": [35, 53, 149, 493, 525], "str_rep": "1 2 2 3 3\n 1 2 2 3 3\n 1 2 4 3 5\n 1 1 4 5 5\n 4 4 4 5 5", "html_rep": "<span style=\"color:#73C6B6\">&#9724;</span> <span style=\"color:#F4D03F\">&#9724;</span> <span style=\"color:#F4D03F\">&#9724;</span> <span style=\"color:#CD6155\">&#9724;</span> <span style=\"color:#CD6155\">&#9724;</span><br/> <span style=\"color:#73C6B6\">&#9724;</span> <span style=\"color:#F4D03F\">&#9724;</span> <span style=\"color:#F4D03F\">&#9724;</span> <span style=\"color:#CD6155\">&#9724;</span> <span style=\"color:#CD6155\">&#9724;</span><br/> <span style=\"color:#73C6B6\">&#9724;</span> <span style=\"color:#F4D03F\">&#9724;</span> <span style=\"color:#A569BD\">&#9724;</span> <span style=\"color:#CD6155\">&#9724;</span> <span style=\"color:#4682B4\">&#9724;</span><br/> <span style=\"color:#73C6B6\">&#9724;</span> <span style=\"color:#73C6B6\">&#9724;</span> <span style=\"color:#A569BD\">&#9724;</span> <span style=\"color:#4682B4\">&#9724;</span> <span style=\"color:#4682B4\">&#9724;</span><br/> <span style=\"color:#A569BD\">&#9724;</span> <span style=\"color:#A569BD\">&#9724;</span> <span style=\"color:#A569BD\">&#9724;</span> <span style=\"color:#4682B4\">&#9724;</span> <span style=\"color:#4682B4\">&#9724;</span>", "name": 731, "id": 1, "children": [{"orbit": 8, "Type": 95, "deg": "6", "tup": [35, 53, 153, 384, 493], "str_rep": "1 2 2 3 3\n 1 2 2 3 4\n 1 2 5 3 4\n 1 1 5 3 4\n 5 5 5 4 4", "html_rep": "<span style=\"color:#73C6B6\">&#9724;</span> <span style=\"color:#F4D03F\">&#9724;</span> <span style=\"color:#F4D03F\">&#9724;</span> <span style=\"color:#CD6155\">&#9724;</span> <span style=\"color:#CD6155\">&#9724;</span><br/> <span style=\"color:#73C6B6\">&#9724;</span> <span style=\"color:#F4D03F\">&#9724;</span> <span style=\"color:#F4D03F\">&#9724;</span> <span style=\"color:#CD6155\">&#9724;</span> <span style=\"color:#A569BD\">&#9724;</span><br/> <span style=\"color:#73C6B6\">&#9724;</span> <span style=\"color:#F4D03F\">&#9724;</span> <span style=\"color:#4682B4\">&#9724;</span> <span style=\"color:#CD6155\">&#9724;</span> <span style=\"color:#A569BD\">&#9724;</span><br/> <span style=\"color:#73C6B6\">&#9724;</span> <span style=\"color:#73C6B6\">&#9724;</span> <span style=\"color:#4682B4\">&#9724;</span> <span style=\"color:#CD6155\">&#9724;</span> <span style=\"color:#A569BD\">&#9724;</span><br/> <span style=\"color:#4682B4\">&#9724;</span> <span style=\"color:#4682B4\">&#9724;</span> <span style=\"color:#4682B4\">&#9724;</span> <span style=\"color:#A569BD\">&#9724;</span> <span style=\"color:#A569BD\">&#9724;</span>", "name": 364, "id": 9}, {"orbit": 8, "Type": 186, "deg": "8", "tup": [36, 53, 149, 485, 525], "str_rep": "1 2 2 3 3\n 1 2 2 3 3\n 1 2 4 3 5\n 1 4 4 5 5\n 1 4 4 5 5", "html_rep": "<span style=\"color:#73C6B6\">&#9724;</span> <span style=\"color:#F4D03F\">&#9724;</span> <span style=\"color:#F4D03F\">&#9724;</span> <span style=\"color:#CD6155\">&#9724;</span> <span style=\"color:#CD6155\">&#9724;</span><br/> <span style=\"color:#73C6B6\">&#9724;</span> <span style=\"color:#F4D03F\">&#9724;</span> <span style=\"color:#F4D03F\">&#9724;</span> <span style=\"color:#CD6155\">&#9724;</span> <span style=\"color:#CD6155\">&#9724;</span><br/> <span style=\"color:#73C6B6\">&#9724;</span> <span style=\"color:#F4D03F\">&#9724;</span> <span style=\"color:#A569BD\">&#9724;</span> <span style=\"color:#CD6155\">&#9724;</span> <span style=\"color:#4682B4\">&#9724;</span><br/> <span style=\"color:#73C6B6\">&#9724;</span> <span style=\"color:#A569BD\">&#9724;</span> <span style=\"color:#A569BD\">&#9724;</span> <span style=\"color:#4682B4\">&#9724;</span> <span style=\"color:#4682B4\">&#9724;</span><br/> <span style=\"color:#73C6B6\">&#9724;</span> <span style=\"color:#A569BD\">&#9724;</span> <span style=\"color:#A569BD\">&#9724;</span> <span style=\"color:#4682B4\">&#9724;</span> <span style=\"color:#4682B4\">&#9724;</span>", "name": 1673, "id": 10}, {"orbit": 8, "Type": 425, "deg": "5", "tup": [16, 124, 149, 493, 525], "str_rep": "1 1 2 3 3\n 1 2 2 3 3\n 1 2 4 3 5\n 1 2 4 5 5\n 4 4 4 5 5", "html_rep": "<span style=\"color:#73C6B6\">&#9724;</span> <span style=\"color:#73C6B6\">&#9724;</span> <span style=\"color:#F4D03F\">&#9724;</span> <span style=\"color:#CD6155\">&#9724;</span> <span style=\"color:#CD6155\">&#9724;</span><br/> <span style=\"color:#73C6B6\">&#9724;</span> <span style=\"color:#F4D03F\">&#9724;</span> <span style=\"color:#F4D03F\">&#9724;</span> <span style=\"color:#CD6155\">&#9724;</span> <span style=\"color:#CD6155\">&#9724;</span><br/> <span style=\"color:#73C6B6\">&#9724;</span> <span style=\"color:#F4D03F\">&#9724;</span> <span style=\"color:#A569BD\">&#9724;</span> <span style=\"color:#CD6155\">&#9724;</span> <span style=\"color:#4682B4\">&#9724;</span><br/> <span style=\"color:#73C6B6\">&#9724;</span> <span style=\"color:#F4D03F\">&#9724;</span> <span style=\"color:#A569BD\">&#9724;</span> <span style=\"color:#4682B4\">&#9724;</span> <span style=\"color:#4682B4\">&#9724;</span><br/> <span style=\"color:#A569BD\">&#9724;</span> <span style=\"color:#A569BD\">&#9724;</span> <span style=\"color:#A569BD\">&#9724;</span> <span style=\"color:#4682B4\">&#9724;</span> <span style=\"color:#4682B4\">&#9724;</span>", "name": 2319, "id": 11}, {"orbit": 8, "Type": 408, "deg": "4", "tup": [35, 44, 184, 493, 525], "str_rep": "1 2 2 2 3\n 1 2 3 3 3\n 1 2 4 3 5\n 1 1 4 5 5\n 4 4 4 5 5", "html_rep": "<span style=\"color:#73C6B6\">&#9724;</span> <span style=\"color:#F4D03F\">&#9724;</span> <span style=\"color:#F4D03F\">&#9724;</span> <span style=\"color:#F4D03F\">&#9724;</span> <span style=\"color:#CD6155\">&#9724;</span><br/> <span style=\"color:#73C6B6\">&#9724;</span> <span style=\"color:#F4D03F\">&#9724;</span> <span style=\"color:#CD6155\">&#9724;</span> <span style=\"color:#CD6155\">&#9724;</span> <span style=\"color:#CD6155\">&#9724;</span><br/> <span style=\"color:#73C6B6\">&#9724;</span> <span style=\"color:#F4D03F\">&#9724;</span> <span style=\"color:#A569BD\">&#9724;</span> <span style=\"color:#CD6155\">&#9724;</span> <span style=\"color:#4682B4\">&#9724;</span><br/> <span style=\"color:#73C6B6\">&#9724;</span> <span style=\"color:#73C6B6\">&#9724;</span> <span style=\"color:#A569BD\">&#9724;</span> <span style=\"color:#4682B4\">&#9724;</span> <span style=\"color:#4682B4\">&#9724;</span><br/> <span style=\"color:#A569BD\">&#9724;</span> <span style=\"color:#A569BD\">&#9724;</span> <span style=\"color:#A569BD\">&#9724;</span> <span style=\"color:#4682B4\">&#9724;</span> <span style=\"color:#4682B4\">&#9724;</span>", "name": 3196, "id": 12}, {"orbit": 8, "Type": 460, "deg": "9", "tup": [8, 149, 223, 493, 525], "str_rep": "1 1 1 2 2\n 3 1 1 2 2\n 3 3 4 2 5\n 3 3 4 5 5\n 4 4 4 5 5", "html_rep": "<span style=\"color:#73C6B6\">&#9724;</span> <span style=\"color:#73C6B6\">&#9724;</span> <span style=\"color:#73C6B6\">&#9724;</span> <span style=\"color:#F4D03F\">&#9724;</span> <span style=\"color:#F4D03F\">&#9724;</span><br/> <span style=\"color:#CD6155\">&#9724;</span> <span style=\"color:#73C6B6\">&#9724;</span> <span style=\"color:#73C6B6\">&#9724;</span> <span style=\"color:#F4D03F\">&#9724;</span> <span style=\"color:#F4D03F\">&#9724;</span><br/> <span style=\"color:#CD6155\">&#9724;</span> <span style=\"color:#CD6155\">&#9724;</span> <span style=\"color:#A569BD\">&#9724;</span> <span style=\"color:#F4D03F\">&#9724;</span> <span style=\"color:#4682B4\">&#9724;</span><br/> <span style=\"color:#CD6155\">&#9724;</span> <span style=\"color:#CD6155\">&#9724;</span> <span style=\"color:#A569BD\">&#9724;</span> <span style=\"color:#4682B4\">&#9724;</span> <span style=\"color:#4682B4\">&#9724;</span><br/> <span style=\"color:#A569BD\">&#9724;</span> <span style=\"color:#A569BD\">&#9724;</span> <span style=\"color:#A569BD\">&#9724;</span> <span style=\"color:#4682B4\">&#9724;</span> <span style=\"color:#4682B4\">&#9724;</span>", "name": 2255, "id": 13}]}, {"orbit": 8, "Type": 141, "deg": "5", "tup": [35, 44, 185, 493, 517], "str_rep": "1 2 2 2 3\n 1 2 3 3 3\n 1 2 4 5 3\n 1 1 4 5 5\n 4 4 4 5 5", "html_rep": "<span style=\"color:#73C6B6\">&#9724;</span> <span style=\"color:#F4D03F\">&#9724;</span> <span style=\"color:#F4D03F\">&#9724;</span> <span style=\"color:#F4D03F\">&#9724;</span> <span style=\"color:#CD6155\">&#9724;</span><br/> <span style=\"color:#73C6B6\">&#9724;</span> <span style=\"color:#F4D03F\">&#9724;</span> <span style=\"color:#CD6155\">&#9724;</span> <span style=\"color:#CD6155\">&#9724;</span> <span style=\"color:#CD6155\">&#9724;</span><br/> <span style=\"color:#73C6B6\">&#9724;</span> <span style=\"color:#F4D03F\">&#9724;</span> <span style=\"color:#A569BD\">&#9724;</span> <span style=\"color:#4682B4\">&#9724;</span> <span style=\"color:#CD6155\">&#9724;</span><br/> <span style=\"color:#73C6B6\">&#9724;</span> <span style=\"color:#73C6B6\">&#9724;</span> <span style=\"color:#A569BD\">&#9724;</span> <span style=\"color:#4682B4\">&#9724;</span> <span style=\"color:#4682B4\">&#9724;</span><br/> <span style=\"color:#A569BD\">&#9724;</span> <span style=\"color:#A569BD\">&#9724;</span> <span style=\"color:#A569BD\">&#9724;</span> <span style=\"color:#4682B4\">&#9724;</span> <span style=\"color:#4682B4\">&#9724;</span>", "name": 923, "id": 2, "children": [{"orbit": 8, "Type": 225, "deg": "6", "tup": [35, 44, 185, 472, 563], "str_rep": "1 2 2 2 3\n 1 2 3 3 3\n 1 2 4 4 3\n 1 1 5 4 4\n 5 5 5 5 4", "html_rep": "<span style=\"color:#73C6B6\">&#9724;</span> <span style=\"color:#F4D03F\">&#9724;</span> <span style=\"color:#F4D03F\">&#9724;</span> <span style=\"color:#F4D03F\">&#9724;</span> <span style=\"color:#CD6155\">&#9724;</span><br/> <span style=\"color:#73C6B6\">&#9724;</span> <span style=\"color:#F4D03F\">&#9724;</span> <span style=\"color:#CD6155\">&#9724;</span> <span style=\"color:#CD6155\">&#9724;</span> <span style=\"color:#CD6155\">&#9724;</span><br/> <span style=\"color:#73C6B6\">&#9724;</span> <span style=\"color:#F4D03F\">&#9724;</span> <span style=\"color:#A569BD\">&#9724;</span> <span style=\"color:#A569BD\">&#9724;</span> <span style=\"color:#CD6155\">&#9724;</span><br/> <span style=\"color:#73C6B6\">&#9724;</span> <span style=\"color:#73C6B6\">&#9724;</span> <span style=\"color:#4682B4\">&#9724;</span> <span style=\"color:#A569BD\">&#9724;</span> <span style=\"color:#A569BD\">&#9724;</span><br/> <span style=\"color:#4682B4\">&#9724;</span> <span style=\"color:#4682B4\">&#9724;</span> <span style=\"color:#4682B4\">&#9724;</span> <span style=\"color:#4682B4\">&#9724;</span> <span style=\"color:#A569BD\">&#9724;</span>", "name": 3293, "id": 14}, {"orbit": 8, "Type": 390, "deg": "10", "tup": [2, 185, 223, 493, 517], "str_rep": "1 1 1 1 2\n 3 1 2 2 2\n 3 3 4 5 2\n 3 3 4 5 5\n 4 4 4 5 5", "html_rep": "<span style=\"color:#73C6B6\">&#9724;</span> <span style=\"color:#73C6B6\">&#9724;</span> <span style=\"color:#73C6B6\">&#9724;</span> <span style=\"color:#73C6B6\">&#9724;</span> <span style=\"color:#F4D03F\">&#9724;</span><br/> <span style=\"color:#CD6155\">&#9724;</span> <span style=\"color:#73C6B6\">&#9724;</span> <span style=\"color:#F4D03F\">&#9724;</span> <span style=\"color:#F4D03F\">&#9724;</span> <span style=\"color:#F4D03F\">&#9724;</span><br/> <span style=\"color:#CD6155\">&#9724;</span> <span style=\"color:#CD6155\">&#9724;</span> <span style=\"color:#A569BD\">&#9724;</span> <span style=\"color:#4682B4\">&#9724;</span> <span style=\"color:#F4D03F\">&#9724;</span><br/> <span style=\"color:#CD6155\">&#9724;</span> <span style=\"color:#CD6155\">&#9724;</span> <span style=\"color:#A569BD\">&#9724;</span> <span style=\"color:#4682B4\">&#9724;</span> <span style=\"color:#4682B4\">&#9724;</span><br/> <span style=\"color:#A569BD\">&#9724;</span> <span style=\"color:#A569BD\">&#9724;</span> <span style=\"color:#A569BD\">&#9724;</span> <span style=\"color:#4682B4\">&#9724;</span> <span style=\"color:#4682B4\">&#9724;</span>", "name": 3880, "id": 15}, {"orbit": 8, "Type": 118, "deg": "6", "tup": [36, 44, 185, 485, 517], "str_rep": "1 2 2 2 3\n 1 2 3 3 3\n 1 2 4 5 3\n 1 4 4 5 5\n 1 4 4 5 5", "html_rep": "<span style=\"color:#73C6B6\">&#9724;</span> <span style=\"color:#F4D03F\">&#9724;</span> <span style=\"color:#F4D03F\">&#9724;</span> <span style=\"color:#F4D03F\">&#9724;</span> <span style=\"color:#CD6155\">&#9724;</span><br/> <span style=\"color:#73C6B6\">&#9724;</span> <span style=\"color:#F4D03F\">&#9724;</span> <span style=\"color:#CD6155\">&#9724;</span> <span style=\"color:#CD6155\">&#9724;</span> <span style=\"color:#CD6155\">&#9724;</span><br/> <span style=\"color:#73C6B6\">&#9724;</span> <span style=\"color:#F4D03F\">&#9724;</span> <span style=\"color:#A569BD\">&#9724;</span> <span style=\"color:#4682B4\">&#9724;</span> <span style=\"color:#CD6155\">&#9724;</span><br/> <span style=\"color:#73C6B6\">&#9724;</span> <span style=\"color:#A569BD\">&#9724;</span> <span style=\"color:#A569BD\">&#9724;</span> <span style=\"color:#4682B4\">&#9724;</span> <span style=\"color:#4682B4\">&#9724;</span><br/> <span style=\"color:#73C6B6\">&#9724;</span> <span style=\"color:#A569BD\">&#9724;</span> <span style=\"color:#A569BD\">&#9724;</span> <span style=\"color:#4682B4\">&#9724;</span> <span style=\"color:#4682B4\">&#9724;</span>", "name": 977, "id": 16}]}, {"orbit": 8, "Type": 474, "deg": "5", "tup": [35, 74, 97, 493, 517], "str_rep": "1 2 3 3 3\n 1 2 2 2 3\n 1 2 4 5 3\n 1 1 4 5 5\n 4 4 4 5 5", "html_rep": "<span style=\"color:#73C6B6\">&#9724;</span> <span style=\"color:#F4D03F\">&#9724;</span> <span style=\"color:#CD6155\">&#9724;</span> <span style=\"color:#CD6155\">&#9724;</span> <span style=\"color:#CD6155\">&#9724;</span><br/> <span style=\"color:#73C6B6\">&#9724;</span> <span style=\"color:#F4D03F\">&#9724;</span> <span style=\"color:#F4D03F\">&#9724;</span> <span style=\"color:#F4D03F\">&#9724;</span> <span style=\"color:#CD6155\">&#9724;</span><br/> <span style=\"color:#73C6B6\">&#9724;</span> <span style=\"color:#F4D03F\">&#9724;</span> <span style=\"color:#A569BD\">&#9724;</span> <span style=\"color:#4682B4\">&#9724;</span> <span style=\"color:#CD6155\">&#9724;</span><br/> <span style=\"color:#73C6B6\">&#9724;</span> <span style=\"color:#73C6B6\">&#9724;</span> <span style=\"color:#A569BD\">&#9724;</span> <span style=\"color:#4682B4\">&#9724;</span> <span style=\"color:#4682B4\">&#9724;</span><br/> <span style=\"color:#A569BD\">&#9724;</span> <span style=\"color:#A569BD\">&#9724;</span> <span style=\"color:#A569BD\">&#9724;</span> <span style=\"color:#4682B4\">&#9724;</span> <span style=\"color:#4682B4\">&#9724;</span>", "name": 1167, "id": 3, "children": [{"orbit": 8, "Type": 168, "deg": "7", "tup": [35, 74, 97, 472, 563], "str_rep": "1 2 3 3 3\n 1 2 2 2 3\n 1 2 4 4 3\n 1 1 5 4 4\n 5 5 5 5 4", "html_rep": "<span style=\"color:#73C6B6\">&#9724;</span> <span style=\"color:#F4D03F\">&#9724;</span> <span style=\"color:#CD6155\">&#9724;</span> <span style=\"color:#CD6155\">&#9724;</span> <span style=\"color:#CD6155\">&#9724;</span><br/> <span style=\"color:#73C6B6\">&#9724;</span> <span style=\"color:#F4D03F\">&#9724;</span> <span style=\"color:#F4D03F\">&#9724;</span> <span style=\"color:#F4D03F\">&#9724;</span> <span style=\"color:#CD6155\">&#9724;</span><br/> <span style=\"color:#73C6B6\">&#9724;</span> <span style=\"color:#F4D03F\">&#9724;</span> <span style=\"color:#A569BD\">&#9724;</span> <span style=\"color:#A569BD\">&#9724;</span> <span style=\"color:#CD6155\">&#9724;</span><br/> <span style=\"color:#73C6B6\">&#9724;</span> <span style=\"color:#73C6B6\">&#9724;</span> <span style=\"color:#4682B4\">&#9724;</span> <span style=\"color:#A569BD\">&#9724;</span> <span style=\"color:#A569BD\">&#9724;</span><br/> <span style=\"color:#4682B4\">&#9724;</span> <span style=\"color:#4682B4\">&#9724;</span> <span style=\"color:#4682B4\">&#9724;</span> <span style=\"color:#4682B4\">&#9724;</span> <span style=\"color:#A569BD\">&#9724;</span>", "name": 550, "id": 17}, {"orbit": 8, "Type": 14, "deg": "6", "tup": [36, 74, 97, 485, 517], "str_rep": "1 2 3 3 3\n 1 2 2 2 3\n 1 2 4 5 3\n 1 4 4 5 5\n 1 4 4 5 5", "html_rep": "<span style=\"color:#73C6B6\">&#9724;</span> <span style=\"color:#F4D03F\">&#9724;</span> <span style=\"color:#CD6155\">&#9724;</span> <span style=\"color:#CD6155\">&#9724;</span> <span style=\"color:#CD6155\">&#9724;</span><br/> <span style=\"color:#73C6B6\">&#9724;</span> <span style=\"color:#F4D03F\">&#9724;</span> <span style=\"color:#F4D03F\">&#9724;</span> <span style=\"color:#F4D03F\">&#9724;</span> <span style=\"color:#CD6155\">&#9724;</span><br/> <span style=\"color:#73C6B6\">&#9724;</span> <span style=\"color:#F4D03F\">&#9724;</span> <span style=\"color:#A569BD\">&#9724;</span> <span style=\"color:#4682B4\">&#9724;</span> <span style=\"color:#CD6155\">&#9724;</span><br/> <span style=\"color:#73C6B6\">&#9724;</span> <span style=\"color:#A569BD\">&#9724;</span> <span style=\"color:#A569BD\">&#9724;</span> <span style=\"color:#4682B4\">&#9724;</span> <span style=\"color:#4682B4\">&#9724;</span><br/> <span style=\"color:#73C6B6\">&#9724;</span> <span style=\"color:#A569BD\">&#9724;</span> <span style=\"color:#A569BD\">&#9724;</span> <span style=\"color:#4682B4\">&#9724;</span> <span style=\"color:#4682B4\">&#9724;</span>", "name": 2751, "id": 18}, {"orbit": 8, "Type": 145, "deg": "4", "tup": [16, 97, 238, 493, 517], "str_rep": "1 1 2 2 2\n 1 3 3 3 2\n 1 3 4 5 2\n 1 3 4 5 5\n 4 4 4 5 5", "html_rep": "<span style=\"color:#73C6B6\">&#9724;</span> <span style=\"color:#73C6B6\">&#9724;</span> <span style=\"color:#F4D03F\">&#9724;</span> <span style=\"color:#F4D03F\">&#9724;</span> <span style=\"color:#F4D03F\">&#9724;</span><br/> <span style=\"color:#73C6B6\">&#9724;</span> <span style=\"color:#CD6155\">&#9724;</span> <span style=\"color:#CD6155\">&#9724;</span> <span style=\"color:#CD6155\">&#9724;</span> <span style=\"color:#F4D03F\">&#9724;</span><br/> <span style=\"color:#73C6B6\">&#9724;</span> <span style=\"color:#CD6155\">&#9724;</span> <span style=\"color:#A569BD\">&#9724;</span> <span style=\"color:#4682B4\">&#9724;</span> <span style=\"color:#F4D03F\">&#9724;</span><br/> <span style=\"color:#73C6B6\">&#9724;</span> <span style=\"color:#CD6155\">&#9724;</span> <span style=\"color:#A569BD\">&#9724;</span> <span style=\"color:#4682B4\">&#9724;</span> <span style=\"color:#4682B4\">&#9724;</span><br/> <span style=\"color:#A569BD\">&#9724;</span> <span style=\"color:#A569BD\">&#9724;</span> <span style=\"color:#A569BD\">&#9724;</span> <span style=\"color:#4682B4\">&#9724;</span> <span style=\"color:#4682B4\">&#9724;</span>", "name": 2405, "id": 19}, {"orbit": 8, "Type": 0, "deg": "7", "tup": [17, 97, 223, 493, 517], "str_rep": "1 1 2 2 2\n 3 1 1 1 2\n 3 3 4 5 2\n 3 3 4 5 5\n 4 4 4 5 5", "html_rep": "<span style=\"color:#73C6B6\">&#9724;</span> <span style=\"color:#73C6B6\">&#9724;</span> <span style=\"color:#F4D03F\">&#9724;</span> <span style=\"color:#F4D03F\">&#9724;</span> <span style=\"color:#F4D03F\">&#9724;</span><br/> <span style=\"color:#CD6155\">&#9724;</span> <span style=\"color:#73C6B6\">&#9724;</span> <span style=\"color:#73C6B6\">&#9724;</span> <span style=\"color:#73C6B6\">&#9724;</span> <span style=\"color:#F4D03F\">&#9724;</span><br/> <span style=\"color:#CD6155\">&#9724;</span> <span style=\"color:#CD6155\">&#9724;</span> <span style=\"color:#A569BD\">&#9724;</span> <span style=\"color:#4682B4\">&#9724;</span> <span style=\"color:#F4D03F\">&#9724;</span><br/> <span style=\"color:#CD6155\">&#9724;</span> <span style=\"color:#CD6155\">&#9724;</span> <span style=\"color:#A569BD\">&#9724;</span> <span style=\"color:#4682B4\">&#9724;</span> <span style=\"color:#4682B4\">&#9724;</span><br/> <span style=\"color:#A569BD\">&#9724;</span> <span style=\"color:#A569BD\">&#9724;</span> <span style=\"color:#A569BD\">&#9724;</span> <span style=\"color:#4682B4\">&#9724;</span> <span style=\"color:#4682B4\">&#9724;</span>", "name": 2139, "id": 20}]}, {"orbit": 8, "Type": 303, "deg": "11", "tup": [8, 150, 223, 493, 517], "str_rep": "1 1 1 2 2\n 3 1 1 2 2\n 3 3 4 5 2\n 3 3 4 5 5\n 4 4 4 5 5", "html_rep": "<span style=\"color:#73C6B6\">&#9724;</span> <span style=\"color:#73C6B6\">&#9724;</span> <span style=\"color:#73C6B6\">&#9724;</span> <span style=\"color:#F4D03F\">&#9724;</span> <span style=\"color:#F4D03F\">&#9724;</span><br/> <span style=\"color:#CD6155\">&#9724;</span> <span style=\"color:#73C6B6\">&#9724;</span> <span style=\"color:#73C6B6\">&#9724;</span> <span style=\"color:#F4D03F\">&#9724;</span> <span style=\"color:#F4D03F\">&#9724;</span><br/> <span style=\"color:#CD6155\">&#9724;</span> <span style=\"color:#CD6155\">&#9724;</span> <span style=\"color:#A569BD\">&#9724;</span> <span style=\"color:#4682B4\">&#9724;</span> <span style=\"color:#F4D03F\">&#9724;</span><br/> <span style=\"color:#CD6155\">&#9724;</span> <span style=\"color:#CD6155\">&#9724;</span> <span style=\"color:#A569BD\">&#9724;</span> <span style=\"color:#4682B4\">&#9724;</span> <span style=\"color:#4682B4\">&#9724;</span><br/> <span style=\"color:#A569BD\">&#9724;</span> <span style=\"color:#A569BD\">&#9724;</span> <span style=\"color:#A569BD\">&#9724;</span> <span style=\"color:#4682B4\">&#9724;</span> <span style=\"color:#4682B4\">&#9724;</span>", "name": 1748, "id": 4, "children": [{"orbit": 8, "Type": 160, "deg": "8", "tup": [8, 150, 228, 437, 517], "str_rep": "1 1 1 2 2\n 3 1 1 2 2\n 3 4 4 5 2\n 3 3 4 5 5\n 3 4 4 5 5", "html_rep": "<span style=\"color:#73C6B6\">&#9724;</span> <span style=\"color:#73C6B6\">&#9724;</span> <span style=\"color:#73C6B6\">&#9724;</span> <span style=\"color:#F4D03F\">&#9724;</span> <span style=\"color:#F4D03F\">&#9724;</span><br/> <span style=\"color:#CD6155\">&#9724;</span> <span style=\"color:#73C6B6\">&#9724;</span> <span style=\"color:#73C6B6\">&#9724;</span> <span style=\"color:#F4D03F\">&#9724;</span> <span style=\"color:#F4D03F\">&#9724;</span><br/> <span style=\"color:#CD6155\">&#9724;</span> <span style=\"color:#A569BD\">&#9724;</span> <span style=\"color:#A569BD\">&#9724;</span> <span style=\"color:#4682B4\">&#9724;</span> <span style=\"color:#F4D03F\">&#9724;</span><br/> <span style=\"color:#CD6155\">&#9724;</span> <span style=\"color:#CD6155\">&#9724;</span> <span style=\"color:#A569BD\">&#9724;</span> <span style=\"color:#4682B4\">&#9724;</span> <span style=\"color:#4682B4\">&#9724;</span><br/> <span style=\"color:#CD6155\">&#9724;</span> <span style=\"color:#A569BD\">&#9724;</span> <span style=\"color:#A569BD\">&#9724;</span> <span style=\"color:#4682B4\">&#9724;</span> <span style=\"color:#4682B4\">&#9724;</span>", "name": 1055, "id": 21}, {"orbit": 8, "Type": 139, "deg": "9", "tup": [6, 150, 263, 493, 517], "str_rep": "1 1 1 2 2\n 1 3 1 2 2\n 3 3 4 5 2\n 3 3 4 5 5\n 4 4 4 5 5", "html_rep": "<span style=\"color:#73C6B6\">&#9724;</span> <span style=\"color:#73C6B6\">&#9724;</span> <span style=\"color:#73C6B6\">&#9724;</span> <span style=\"color:#F4D03F\">&#9724;</span> <span style=\"color:#F4D03F\">&#9724;</span><br/> <span style=\"color:#73C6B6\">&#9724;</span> <span style=\"color:#CD6155\">&#9724;</span> <span style=\"color:#73C6B6\">&#9724;</span> <span style=\"color:#F4D03F\">&#9724;</span> <span style=\"color:#F4D03F\">&#9724;</span><br/> <span style=\"color:#CD6155\">&#9724;</span> <span style=\"color:#CD6155\">&#9724;</span> <span style=\"color:#A569BD\">&#9724;</span> <span style=\"color:#4682B4\">&#9724;</span> <span style=\"color:#F4D03F\">&#9724;</span><br/> <span style=\"color:#CD6155\">&#9724;</span> <span style=\"color:#CD6155\">&#9724;</span> <span style=\"color:#A569BD\">&#9724;</span> <span style=\"color:#4682B4\">&#9724;</span> <span style=\"color:#4682B4\">&#9724;</span><br/> <span style=\"color:#A569BD\">&#9724;</span> <span style=\"color:#A569BD\">&#9724;</span> <span style=\"color:#A569BD\">&#9724;</span> <span style=\"color:#4682B4\">&#9724;</span> <span style=\"color:#4682B4\">&#9724;</span>", "name": 1101, "id": 22}, {"orbit": 8, "Type": 102, "deg": "8", "tup": [8, 155, 223, 372, 493], "str_rep": "1 1 1 2 2\n 3 1 1 4 2\n 3 3 5 4 2\n 3 3 5 4 2\n 5 5 5 4 4", "html_rep": "<span style=\"color:#73C6B6\">&#9724;</span> <span style=\"color:#73C6B6\">&#9724;</span> <span style=\"color:#73C6B6\">&#9724;</span> <span style=\"color:#F4D03F\">&#9724;</span> <span style=\"color:#F4D03F\">&#9724;</span><br/> <span style=\"color:#CD6155\">&#9724;</span> <span style=\"color:#73C6B6\">&#9724;</span> <span style=\"color:#73C6B6\">&#9724;</span> <span style=\"color:#A569BD\">&#9724;</span> <span style=\"color:#F4D03F\">&#9724;</span><br/> <span style=\"color:#CD6155\">&#9724;</span> <span style=\"color:#CD6155\">&#9724;</span> <span style=\"color:#4682B4\">&#9724;</span> <span style=\"color:#A569BD\">&#9724;</span> <span style=\"color:#F4D03F\">&#9724;</span><br/> <span style=\"color:#CD6155\">&#9724;</span> <span style=\"color:#CD6155\">&#9724;</span> <span style=\"color:#4682B4\">&#9724;</span> <span style=\"color:#A569BD\">&#9724;</span> <span style=\"color:#F4D03F\">&#9724;</span><br/> <span style=\"color:#4682B4\">&#9724;</span> <span style=\"color:#4682B4\">&#9724;</span> <span style=\"color:#4682B4\">&#9724;</span> <span style=\"color:#A569BD\">&#9724;</span> <span style=\"color:#A569BD\">&#9724;</span>", "name": 1468, "id": 23}, {"orbit": 8, "Type": 235, "deg": "12", "tup": [8, 150, 221, 517, 538], "str_rep": "1 1 1 2 2\n 3 1 1 2 2\n 3 3 3 4 2\n 5 3 5 4 4\n 5 5 5 4 4", "html_rep": "<span style=\"color:#73C6B6\">&#9724;</span> <span style=\"color:#73C6B6\">&#9724;</span> <span style=\"color:#73C6B6\">&#9724;</span> <span style=\"color:#F4D03F\">&#9724;</span> <span style=\"color:#F4D03F\">&#9724;</span><br/> <span style=\"color:#CD6155\">&#9724;</span> <span style=\"color:#73C6B6\">&#9724;</span> <span style=\"color:#73C6B6\">&#9724;</span> <span style=\"color:#F4D03F\">&#9724;</span> <span style=\"color:#F4D03F\">&#9724;</span><br/> <span style=\"color:#CD6155\">&#9724;</span> <span style=\"color:#CD6155\">&#9724;</span> <span style=\"color:#CD6155\">&#9724;</span> <span style=\"color:#A569BD\">&#9724;</span> <span style=\"color:#F4D03F\">&#9724;</span><br/> <span style=\"color:#4682B4\">&#9724;</span> <span style=\"color:#CD6155\">&#9724;</span> <span style=\"color:#4682B4\">&#9724;</span> <span style=\"color:#A569BD\">&#9724;</span> <span style=\"color:#A569BD\">&#9724;</span><br/> <span style=\"color:#4682B4\">&#9724;</span> <span style=\"color:#4682B4\">&#9724;</span> <span style=\"color:#4682B4\">&#9724;</span> <span style=\"color:#A569BD\">&#9724;</span> <span style=\"color:#A569BD\">&#9724;</span>", "name": 2966, "id": 24}, {"orbit": 8, "Type": 502, "deg": "12", "tup": [8, 150, 224, 485, 517], "str_rep": "1 1 1 2 2\n 3 1 1 2 2\n 3 3 4 5 2\n 3 4 4 5 5\n 3 4 4 5 5", "html_rep": "<span style=\"color:#73C6B6\">&#9724;</span> <span style=\"color:#73C6B6\">&#9724;</span> <span style=\"color:#73C6B6\">&#9724;</span> <span style=\"color:#F4D03F\">&#9724;</span> <span style=\"color:#F4D03F\">&#9724;</span><br/> <span style=\"color:#CD6155\">&#9724;</span> <span style=\"color:#73C6B6\">&#9724;</span> <span style=\"color:#73C6B6\">&#9724;</span> <span style=\"color:#F4D03F\">&#9724;</span> <span style=\"color:#F4D03F\">&#9724;</span><br/> <span style=\"color:#CD6155\">&#9724;</span> <span style=\"color:#CD6155\">&#9724;</span> <span style=\"color:#A569BD\">&#9724;</span> <span style=\"color:#4682B4\">&#9724;</span> <span style=\"color:#F4D03F\">&#9724;</span><br/> <span style=\"color:#CD6155\">&#9724;</span> <span style=\"color:#A569BD\">&#9724;</span> <span style=\"color:#A569BD\">&#9724;</span> <span style=\"color:#4682B4\">&#9724;</span> <span style=\"color:#4682B4\">&#9724;</span><br/> <span style=\"color:#CD6155\">&#9724;</span> <span style=\"color:#A569BD\">&#9724;</span> <span style=\"color:#A569BD\">&#9724;</span> <span style=\"color:#4682B4\">&#9724;</span> <span style=\"color:#4682B4\">&#9724;</span>", "name": 3665, "id": 25}, {"orbit": 8, "Type": 366, "deg": "13", "tup": [8, 150, 220, 517, 549], "str_rep": "1 1 1 2 2\n 3 1 1 2 2\n 3 3 3 4 2\n 3 5 5 4 4\n 5 5 5 4 4", "html_rep": "<span style=\"color:#73C6B6\">&#9724;</span> <span style=\"color:#73C6B6\">&#9724;</span> <span style=\"color:#73C6B6\">&#9724;</span> <span style=\"color:#F4D03F\">&#9724;</span> <span style=\"color:#F4D03F\">&#9724;</span><br/> <span style=\"color:#CD6155\">&#9724;</span> <span style=\"color:#73C6B6\">&#9724;</span> <span style=\"color:#73C6B6\">&#9724;</span> <span style=\"color:#F4D03F\">&#9724;</span> <span style=\"color:#F4D03F\">&#9724;</span><br/> <span style=\"color:#CD6155\">&#9724;</span> <span style=\"color:#CD6155\">&#9724;</span> <span style=\"color:#CD6155\">&#9724;</span> <span style=\"color:#A569BD\">&#9724;</span> <span style=\"color:#F4D03F\">&#9724;</span><br/> <span style=\"color:#CD6155\">&#9724;</span> <span style=\"color:#4682B4\">&#9724;</span> <span style=\"color:#4682B4\">&#9724;</span> <span style=\"color:#A569BD\">&#9724;</span> <span style=\"color:#A569BD\">&#9724;</span><br/> <span style=\"color:#4682B4\">&#9724;</span> <span style=\"color:#4682B4\">&#9724;</span> <span style=\"color:#4682B4\">&#9724;</span> <span style=\"color:#A569BD\">&#9724;</span> <span style=\"color:#A569BD\">&#9724;</span>", "name": 3526, "id": 26}, {"orbit": 8, "Type": 509, "deg": "8", "tup": [8, 150, 223, 472, 563], "str_rep": "1 1 1 2 2\n 3 1 1 2 2\n 3 3 4 4 2\n 3 3 5 4 4\n 5 5 5 5 4", "html_rep": "<span style=\"color:#73C6B6\">&#9724;</span> <span style=\"color:#73C6B6\">&#9724;</span> <span style=\"color:#73C6B6\">&#9724;</span> <span style=\"color:#F4D03F\">&#9724;</span> <span style=\"color:#F4D03F\">&#9724;</span><br/> <span style=\"color:#CD6155\">&#9724;</span> <span style=\"color:#73C6B6\">&#9724;</span> <span style=\"color:#73C6B6\">&#9724;</span> <span style=\"color:#F4D03F\">&#9724;</span> <span style=\"color:#F4D03F\">&#9724;</span><br/> <span style=\"color:#CD6155\">&#9724;</span> <span style=\"color:#CD6155\">&#9724;</span> <span style=\"color:#A569BD\">&#9724;</span> <span style=\"color:#A569BD\">&#9724;</span> <span style=\"color:#F4D03F\">&#9724;</span><br/> <span style=\"color:#CD6155\">&#9724;</span> <span style=\"color:#CD6155\">&#9724;</span> <span style=\"color:#4682B4\">&#9724;</span> <span style=\"color:#A569BD\">&#9724;</span> <span style=\"color:#A569BD\">&#9724;</span><br/> <span style=\"color:#4682B4\">&#9724;</span> <span style=\"color:#4682B4\">&#9724;</span> <span style=\"color:#4682B4\">&#9724;</span> <span style=\"color:#4682B4\">&#9724;</span> <span style=\"color:#A569BD\">&#9724;</span>", "name": 1794, "id": 27}]}, {"orbit": 8, "Type": 397, "deg": "10", "tup": [36, 53, 150, 485, 517], "str_rep": "1 2 2 3 3\n 1 2 2 3 3\n 1 2 4 5 3\n 1 4 4 5 5\n 1 4 4 5 5", "html_rep": "<span style=\"color:#73C6B6\">&#9724;</span> <span style=\"color:#F4D03F\">&#9724;</span> <span style=\"color:#F4D03F\">&#9724;</span> <span style=\"color:#CD6155\">&#9724;</span> <span style=\"color:#CD6155\">&#9724;</span><br/> <span style=\"color:#73C6B6\">&#9724;</span> <span style=\"color:#F4D03F\">&#9724;</span> <span style=\"color:#F4D03F\">&#9724;</span> <span style=\"color:#CD6155\">&#9724;</span> <span style=\"color:#CD6155\">&#9724;</span><br/> <span style=\"color:#73C6B6\">&#9724;</span> <span style=\"color:#F4D03F\">&#9724;</span> <span style=\"color:#A569BD\">&#9724;</span> <span style=\"color:#4682B4\">&#9724;</span> <span style=\"color:#CD6155\">&#9724;</span><br/> <span style=\"color:#73C6B6\">&#9724;</span> <span style=\"color:#A569BD\">&#9724;</span> <span style=\"color:#A569BD\">&#9724;</span> <span style=\"color:#4682B4\">&#9724;</span> <span style=\"color:#4682B4\">&#9724;</span><br/> <span style=\"color:#73C6B6\">&#9724;</span> <span style=\"color:#A569BD\">&#9724;</span> <span style=\"color:#A569BD\">&#9724;</span> <span style=\"color:#4682B4\">&#9724;</span> <span style=\"color:#4682B4\">&#9724;</span>", "name": 2034, "id": 5, "children": [{"orbit": 8, "Type": 170, "deg": "6", "tup": [36, 53, 155, 372, 485], "str_rep": "1 2 2 3 3\n 1 2 2 4 3\n 1 2 5 4 3\n 1 5 5 4 3\n 1 5 5 4 4", "html_rep": "<span style=\"color:#73C6B6\">&#9724;</span> <span style=\"color:#F4D03F\">&#9724;</span> <span style=\"color:#F4D03F\">&#9724;</span> <span style=\"color:#CD6155\">&#9724;</span> <span style=\"color:#CD6155\">&#9724;</span><br/> <span style=\"color:#73C6B6\">&#9724;</span> <span style=\"color:#F4D03F\">&#9724;</span> <span style=\"color:#F4D03F\">&#9724;</span> <span style=\"color:#A569BD\">&#9724;</span> <span style=\"color:#CD6155\">&#9724;</span><br/> <span style=\"color:#73C6B6\">&#9724;</span> <span style=\"color:#F4D03F\">&#9724;</span> <span style=\"color:#4682B4\">&#9724;</span> <span style=\"color:#A569BD\">&#9724;</span> <span style=\"color:#CD6155\">&#9724;</span><br/> <span style=\"color:#73C6B6\">&#9724;</span> <span style=\"color:#4682B4\">&#9724;</span> <span style=\"color:#4682B4\">&#9724;</span> <span style=\"color:#A569BD\">&#9724;</span> <span style=\"color:#CD6155\">&#9724;</span><br/> <span style=\"color:#73C6B6\">&#9724;</span> <span style=\"color:#4682B4\">&#9724;</span> <span style=\"color:#4682B4\">&#9724;</span> <span style=\"color:#A569BD\">&#9724;</span> <span style=\"color:#A569BD\">&#9724;</span>", "name": 210, "id": 28}, {"orbit": 8, "Type": 90, "deg": "6", "tup": [36, 53, 150, 472, 550], "str_rep": "1 2 2 3 3\n 1 2 2 3 3\n 1 2 4 4 3\n 1 5 5 4 4\n 1 5 5 5 4", "html_rep": "<span style=\"color:#73C6B6\">&#9724;</span> <span style=\"color:#F4D03F\">&#9724;</span> <span style=\"color:#F4D03F\">&#9724;</span> <span style=\"color:#CD6155\">&#9724;</span> <span style=\"color:#CD6155\">&#9724;</span><br/> <span style=\"color:#73C6B6\">&#9724;</span> <span style=\"color:#F4D03F\">&#9724;</span> <span style=\"color:#F4D03F\">&#9724;</span> <span style=\"color:#CD6155\">&#9724;</span> <span style=\"color:#CD6155\">&#9724;</span><br/> <span style=\"color:#73C6B6\">&#9724;</span> <span style=\"color:#F4D03F\">&#9724;</span> <span style=\"color:#A569BD\">&#9724;</span> <span style=\"color:#A569BD\">&#9724;</span> <span style=\"color:#CD6155\">&#9724;</span><br/> <span style=\"color:#73C6B6\">&#9724;</span> <span style=\"color:#4682B4\">&#9724;</span> <span style=\"color:#4682B4\">&#9724;</span> <span style=\"color:#A569BD\">&#9724;</span> <span style=\"color:#A569BD\">&#9724;</span><br/> <span style=\"color:#73C6B6\">&#9724;</span> <span style=\"color:#4682B4\">&#9724;</span> <span style=\"color:#4682B4\">&#9724;</span> <span style=\"color:#4682B4\">&#9724;</span> <span style=\"color:#A569BD\">&#9724;</span>", "name": 533, "id": 29}, {"orbit": 8, "Type": 186, "deg": "8", "tup": [36, 54, 150, 451, 517], "str_rep": "1 2 2 3 3\n 1 2 2 3 3\n 1 4 2 5 3\n 1 4 4 5 5\n 1 4 4 5 5", "html_rep": "<span style=\"color:#73C6B6\">&#9724;</span> <span style=\"color:#F4D03F\">&#9724;</span> <span style=\"color:#F4D03F\">&#9724;</span> <span style=\"color:#CD6155\">&#9724;</span> <span style=\"color:#CD6155\">&#9724;</span><br/> <span style=\"color:#73C6B6\">&#9724;</span> <span style=\"color:#F4D03F\">&#9724;</span> <span style=\"color:#F4D03F\">&#9724;</span> <span style=\"color:#CD6155\">&#9724;</span> <span style=\"color:#CD6155\">&#9724;</span><br/> <span style=\"color:#73C6B6\">&#9724;</span> <span style=\"color:#A569BD\">&#9724;</span> <span style=\"color:#F4D03F\">&#9724;</span> <span style=\"color:#4682B4\">&#9724;</span> <span style=\"color:#CD6155\">&#9724;</span><br/> <span style=\"color:#73C6B6\">&#9724;</span> <span style=\"color:#A569BD\">&#9724;</span> <span style=\"color:#A569BD\">&#9724;</span> <span style=\"color:#4682B4\">&#9724;</span> <span style=\"color:#4682B4\">&#9724;</span><br/> <span style=\"color:#73C6B6\">&#9724;</span> <span style=\"color:#A569BD\">&#9724;</span> <span style=\"color:#A569BD\">&#9724;</span> <span style=\"color:#4682B4\">&#9724;</span> <span style=\"color:#4682B4\">&#9724;</span>", "name": 1391, "id": 30}, {"orbit": 8, "Type": 135, "deg": "5", "tup": [36, 53, 150, 464, 566], "str_rep": "1 2 2 3 3\n 1 2 2 3 3\n 1 2 4 4 3\n 1 4 4 5 5\n 1 4 5 5 5", "html_rep": "<span style=\"color:#73C6B6\">&#9724;</span> <span style=\"color:#F4D03F\">&#9724;</span> <span style=\"color:#F4D03F\">&#9724;</span> <span style=\"color:#CD6155\">&#9724;</span> <span style=\"color:#CD6155\">&#9724;</span><br/> <span style=\"color:#73C6B6\">&#9724;</span> <span style=\"color:#F4D03F\">&#9724;</span> <span style=\"color:#F4D03F\">&#9724;</span> <span style=\"color:#CD6155\">&#9724;</span> <span style=\"color:#CD6155\">&#9724;</span><br/> <span style=\"color:#73C6B6\">&#9724;</span> <span style=\"color:#F4D03F\">&#9724;</span> <span style=\"color:#A569BD\">&#9724;</span> <span style=\"color:#A569BD\">&#9724;</span> <span style=\"color:#CD6155\">&#9724;</span><br/> <span style=\"color:#73C6B6\">&#9724;</span> <span style=\"color:#A569BD\">&#9724;</span> <span style=\"color:#A569BD\">&#9724;</span> <span style=\"color:#4682B4\">&#9724;</span> <span style=\"color:#4682B4\">&#9724;</span><br/> <span style=\"color:#73C6B6\">&#9724;</span> <span style=\"color:#A569BD\">&#9724;</span> <span style=\"color:#4682B4\">&#9724;</span> <span style=\"color:#4682B4\">&#9724;</span> <span style=\"color:#4682B4\">&#9724;</span>", "name": 1860, "id": 31}, {"orbit": 8, "Type": 402, "deg": "5", "tup": [36, 57, 150, 335, 517], "str_rep": "1 2 2 3 3\n 1 2 4 3 3\n 1 2 4 5 3\n 1 2 4 5 5\n 1 4 4 5 5", "html_rep": "<span style=\"color:#73C6B6\">&#9724;</span> <span style=\"color:#F4D03F\">&#9724;</span> <span style=\"color:#F4D03F\">&#9724;</span> <span style=\"color:#CD6155\">&#9724;</span> <span style=\"color:#CD6155\">&#9724;</span><br/> <span style=\"color:#73C6B6\">&#9724;</span> <span style=\"color:#F4D03F\">&#9724;</span> <span style=\"color:#A569BD\">&#9724;</span> <span style=\"color:#CD6155\">&#9724;</span> <span style=\"color:#CD6155\">&#9724;</span><br/> <span style=\"color:#73C6B6\">&#9724;</span> <span style=\"color:#F4D03F\">&#9724;</span> <span style=\"color:#A569BD\">&#9724;</span> <span style=\"color:#4682B4\">&#9724;</span> <span style=\"color:#CD6155\">&#9724;</span><br/> <span style=\"color:#73C6B6\">&#9724;</span> <span style=\"color:#F4D03F\">&#9724;</span> <span style=\"color:#A569BD\">&#9724;</span> <span style=\"color:#4682B4\">&#9724;</span> <span style=\"color:#4682B4\">&#9724;</span><br/> <span style=\"color:#73C6B6\">&#9724;</span> <span style=\"color:#A569BD\">&#9724;</span> <span style=\"color:#A569BD\">&#9724;</span> <span style=\"color:#4682B4\">&#9724;</span> <span style=\"color:#4682B4\">&#9724;</span>", "name": 3560, "id": 32}]}, {"orbit": 8, "Type": 316, "deg": "7", "tup": [35, 53, 150, 472, 563], "str_rep": "1 2 2 3 3\n 1 2 2 3 3\n 1 2 4 4 3\n 1 1 5 4 4\n 5 5 5 5 4", "html_rep": "<span style=\"color:#73C6B6\">&#9724;</span> <span style=\"color:#F4D03F\">&#9724;</span> <span style=\"color:#F4D03F\">&#9724;</span> <span style=\"color:#CD6155\">&#9724;</span> <span style=\"color:#CD6155\">&#9724;</span><br/> <span style=\"color:#73C6B6\">&#9724;</span> <span style=\"color:#F4D03F\">&#9724;</span> <span style=\"color:#F4D03F\">&#9724;</span> <span style=\"color:#CD6155\">&#9724;</span> <span style=\"color:#CD6155\">&#9724;</span><br/> <span style=\"color:#73C6B6\">&#9724;</span> <span style=\"color:#F4D03F\">&#9724;</span> <span style=\"color:#A569BD\">&#9724;</span> <span style=\"color:#A569BD\">&#9724;</span> <span style=\"color:#CD6155\">&#9724;</span><br/> <span style=\"color:#73C6B6\">&#9724;</span> <span style=\"color:#73C6B6\">&#9724;</span> <span style=\"color:#4682B4\">&#9724;</span> <span style=\"color:#A569BD\">&#9724;</span> <span style=\"color:#A569BD\">&#9724;</span><br/> <span style=\"color:#4682B4\">&#9724;</span> <span style=\"color:#4682B4\">&#9724;</span> <span style=\"color:#4682B4\">&#9724;</span> <span style=\"color:#4682B4\">&#9724;</span> <span style=\"color:#A569BD\">&#9724;</span>", "name": 2582, "id": 6, "children": [{"orbit": 8, "Type": 246, "deg": "8", "tup": [35, 53, 150, 466, 570], "str_rep": "1 2 2 3 3\n 1 2 2 3 3\n 1 2 4 4 3\n 1 1 4 4 4\n 5 5 5 5 5", "html_rep": "<span style=\"color:#73C6B6\">&#9724;</span> <span style=\"color:#F4D03F\">&#9724;</span> <span style=\"color:#F4D03F\">&#9724;</span> <span style=\"color:#CD6155\">&#9724;</span> <span style=\"color:#CD6155\">&#9724;</span><br/> <span style=\"color:#73C6B6\">&#9724;</span> <span style=\"color:#F4D03F\">&#9724;</span> <span style=\"color:#F4D03F\">&#9724;</span> <span style=\"color:#CD6155\">&#9724;</span> <span style=\"color:#CD6155\">&#9724;</span><br/> <span style=\"color:#73C6B6\">&#9724;</span> <span style=\"color:#F4D03F\">&#9724;</span> <span style=\"color:#A569BD\">&#9724;</span> <span style=\"color:#A569BD\">&#9724;</span> <span style=\"color:#CD6155\">&#9724;</span><br/> <span style=\"color:#73C6B6\">&#9724;</span> <span style=\"color:#73C6B6\">&#9724;</span> <span style=\"color:#A569BD\">&#9724;</span> <span style=\"color:#A569BD\">&#9724;</span> <span style=\"color:#A569BD\">&#9724;</span><br/> <span style=\"color:#4682B4\">&#9724;</span> <span style=\"color:#4682B4\">&#9724;</span> <span style=\"color:#4682B4\">&#9724;</span> <span style=\"color:#4682B4\">&#9724;</span> <span style=\"color:#4682B4\">&#9724;</span>", "name": 2482, "id": 33}, {"orbit": 8, "Type": 2, "deg": "5", "tup": [16, 124, 150, 472, 563], "str_rep": "1 1 2 3 3\n 1 2 2 3 3\n 1 2 4 4 3\n 1 2 5 4 4\n 5 5 5 5 4", "html_rep": "<span style=\"color:#73C6B6\">&#9724;</span> <span style=\"color:#73C6B6\">&#9724;</span> <span style=\"color:#F4D03F\">&#9724;</span> <span style=\"color:#CD6155\">&#9724;</span> <span style=\"color:#CD6155\">&#9724;</span><br/> <span style=\"color:#73C6B6\">&#9724;</span> <span style=\"color:#F4D03F\">&#9724;</span> <span style=\"color:#F4D03F\">&#9724;</span> <span style=\"color:#CD6155\">&#9724;</span> <span style=\"color:#CD6155\">&#9724;</span><br/> <span style=\"color:#73C6B6\">&#9724;</span> <span style=\"color:#F4D03F\">&#9724;</span> <span style=\"color:#A569BD\">&#9724;</span> <span style=\"color:#A569BD\">&#9724;</span> <span style=\"color:#CD6155\">&#9724;</span><br/> <span style=\"color:#73C6B6\">&#9724;</span> <span style=\"color:#F4D03F\">&#9724;</span> <span style=\"color:#4682B4\">&#9724;</span> <span style=\"color:#A569BD\">&#9724;</span> <span style=\"color:#A569BD\">&#9724;</span><br/> <span style=\"color:#4682B4\">&#9724;</span> <span style=\"color:#4682B4\">&#9724;</span> <span style=\"color:#4682B4\">&#9724;</span> <span style=\"color:#4682B4\">&#9724;</span> <span style=\"color:#A569BD\">&#9724;</span>", "name": 2605, "id": 34}]}, {"orbit": 8, "Type": 149, "deg": "7", "tup": [16, 124, 150, 493, 517], "str_rep": "1 1 2 3 3\n 1 2 2 3 3\n 1 2 4 5 3\n 1 2 4 5 5\n 4 4 4 5 5", "html_rep": "<span style=\"color:#73C6B6\">&#9724;</span> <span style=\"color:#73C6B6\">&#9724;</span> <span style=\"color:#F4D03F\">&#9724;</span> <span style=\"color:#CD6155\">&#9724;</span> <span style=\"color:#CD6155\">&#9724;</span><br/> <span style=\"color:#73C6B6\">&#9724;</span> <span style=\"color:#F4D03F\">&#9724;</span> <span style=\"color:#F4D03F\">&#9724;</span> <span style=\"color:#CD6155\">&#9724;</span> <span style=\"color:#CD6155\">&#9724;</span><br/> <span style=\"color:#73C6B6\">&#9724;</span> <span style=\"color:#F4D03F\">&#9724;</span> <span style=\"color:#A569BD\">&#9724;</span> <span style=\"color:#4682B4\">&#9724;</span> <span style=\"color:#CD6155\">&#9724;</span><br/> <span style=\"color:#73C6B6\">&#9724;</span> <span style=\"color:#F4D03F\">&#9724;</span> <span style=\"color:#A569BD\">&#9724;</span> <span style=\"color:#4682B4\">&#9724;</span> <span style=\"color:#4682B4\">&#9724;</span><br/> <span style=\"color:#A569BD\">&#9724;</span> <span style=\"color:#A569BD\">&#9724;</span> <span style=\"color:#A569BD\">&#9724;</span> <span style=\"color:#4682B4\">&#9724;</span> <span style=\"color:#4682B4\">&#9724;</span>", "name": 3951, "id": 7, "children": [{"orbit": 8, "Type": 484, "deg": "7", "tup": [7, 150, 249, 493, 517], "str_rep": "1 1 1 2 2\n 1 3 3 2 2\n 1 3 4 5 2\n 3 3 4 5 5\n 4 4 4 5 5", "html_rep": "<span style=\"color:#73C6B6\">&#9724;</span> <span style=\"color:#73C6B6\">&#9724;</span> <span style=\"color:#73C6B6\">&#9724;</span> <span style=\"color:#F4D03F\">&#9724;</span> <span style=\"color:#F4D03F\">&#9724;</span><br/> <span style=\"color:#73C6B6\">&#9724;</span> <span style=\"color:#CD6155\">&#9724;</span> <span style=\"color:#CD6155\">&#9724;</span> <span style=\"color:#F4D03F\">&#9724;</span> <span style=\"color:#F4D03F\">&#9724;</span><br/> <span style=\"color:#73C6B6\">&#9724;</span> <span style=\"color:#CD6155\">&#9724;</span> <span style=\"color:#A569BD\">&#9724;</span> <span style=\"color:#4682B4\">&#9724;</span> <span style=\"color:#F4D03F\">&#9724;</span><br/> <span style=\"color:#CD6155\">&#9724;</span> <span style=\"color:#CD6155\">&#9724;</span> <span style=\"color:#A569BD\">&#9724;</span> <span style=\"color:#4682B4\">&#9724;</span> <span style=\"color:#4682B4\">&#9724;</span><br/> <span style=\"color:#A569BD\">&#9724;</span> <span style=\"color:#A569BD\">&#9724;</span> <span style=\"color:#A569BD\">&#9724;</span> <span style=\"color:#4682B4\">&#9724;</span> <span style=\"color:#4682B4\">&#9724;</span>", "name": 1224, "id": 35}, {"orbit": 8, "Type": 66, "deg": "8", "tup": [16, 123, 150, 517, 549], "str_rep": "1 1 2 3 3\n 1 2 2 3 3\n 1 2 2 4 3\n 1 5 5 4 4\n 5 5 5 4 4", "html_rep": "<span style=\"color:#73C6B6\">&#9724;</span> <span style=\"color:#73C6B6\">&#9724;</span> <span style=\"color:#F4D03F\">&#9724;</span> <span style=\"color:#CD6155\">&#9724;</span> <span style=\"color:#CD6155\">&#9724;</span><br/> <span style=\"color:#73C6B6\">&#9724;</span> <span style=\"color:#F4D03F\">&#9724;</span> <span style=\"color:#F4D03F\">&#9724;</span> <span style=\"color:#CD6155\">&#9724;</span> <span style=\"color:#CD6155\">&#9724;</span><br/> <span style=\"color:#73C6B6\">&#9724;</span> <span style=\"color:#F4D03F\">&#9724;</span> <span style=\"color:#F4D03F\">&#9724;</span> <span style=\"color:#A569BD\">&#9724;</span> <span style=\"color:#CD6155\">&#9724;</span><br/> <span style=\"color:#73C6B6\">&#9724;</span> <span style=\"color:#4682B4\">&#9724;</span> <span style=\"color:#4682B4\">&#9724;</span> <span style=\"color:#A569BD\">&#9724;</span> <span style=\"color:#A569BD\">&#9724;</span><br/> <span style=\"color:#4682B4\">&#9724;</span> <span style=\"color:#4682B4\">&#9724;</span> <span style=\"color:#4682B4\">&#9724;</span> <span style=\"color:#A569BD\">&#9724;</span> <span style=\"color:#A569BD\">&#9724;</span>", "name": 3038, "id": 36}, {"orbit": 8, "Type": 473, "deg": "5", "tup": [16, 124, 155, 372, 493], "str_rep": "1 1 2 3 3\n 1 2 2 4 3\n 1 2 5 4 3\n 1 2 5 4 3\n 5 5 5 4 4", "html_rep": "<span style=\"color:#73C6B6\">&#9724;</span> <span style=\"color:#73C6B6\">&#9724;</span> <span style=\"color:#F4D03F\">&#9724;</span> <span style=\"color:#CD6155\">&#9724;</span> <span style=\"color:#CD6155\">&#9724;</span><br/> <span style=\"color:#73C6B6\">&#9724;</span> <span style=\"color:#F4D03F\">&#9724;</span> <span style=\"color:#F4D03F\">&#9724;</span> <span style=\"color:#A569BD\">&#9724;</span> <span style=\"color:#CD6155\">&#9724;</span><br/> <span style=\"color:#73C6B6\">&#9724;</span> <span style=\"color:#F4D03F\">&#9724;</span> <span style=\"color:#4682B4\">&#9724;</span> <span style=\"color:#A569BD\">&#9724;</span> <span style=\"color:#CD6155\">&#9724;</span><br/> <span style=\"color:#73C6B6\">&#9724;</span> <span style=\"color:#F4D03F\">&#9724;</span> <span style=\"color:#4682B4\">&#9724;</span> <span style=\"color:#A569BD\">&#9724;</span> <span style=\"color:#CD6155\">&#9724;</span><br/> <span style=\"color:#4682B4\">&#9724;</span> <span style=\"color:#4682B4\">&#9724;</span> <span style=\"color:#4682B4\">&#9724;</span> <span style=\"color:#A569BD\">&#9724;</span> <span style=\"color:#A569BD\">&#9724;</span>", "name": 3737, "id": 37}]}, {"orbit": 8, "Type": 483, "deg": "5", "tup": [35, 53, 155, 372, 493], "str_rep": "1 2 2 3 3\n 1 2 2 4 3\n 1 2 5 4 3\n 1 1 5 4 3\n 5 5 5 4 4", "html_rep": "<span style=\"color:#73C6B6\">&#9724;</span> <span style=\"color:#F4D03F\">&#9724;</span> <span style=\"color:#F4D03F\">&#9724;</span> <span style=\"color:#CD6155\">&#9724;</span> <span style=\"color:#CD6155\">&#9724;</span><br/> <span style=\"color:#73C6B6\">&#9724;</span> <span style=\"color:#F4D03F\">&#9724;</span> <span style=\"color:#F4D03F\">&#9724;</span> <span style=\"color:#A569BD\">&#9724;</span> <span style=\"color:#CD6155\">&#9724;</span><br/> <span style=\"color:#73C6B6\">&#9724;</span> <span style=\"color:#F4D03F\">&#9724;</span> <span style=\"color:#4682B4\">&#9724;</span> <span style=\"color:#A569BD\">&#9724;</span> <span style=\"color:#CD6155\">&#9724;</span><br/> <span style=\"color:#73C6B6\">&#9724;</span> <span style=\"color:#73C6B6\">&#9724;</span> <span style=\"color:#4682B4\">&#9724;</span> <span style=\"color:#A569BD\">&#9724;</span> <span style=\"color:#CD6155\">&#9724;</span><br/> <span style=\"color:#4682B4\">&#9724;</span> <span style=\"color:#4682B4\">&#9724;</span> <span style=\"color:#4682B4\">&#9724;</span> <span style=\"color:#A569BD\">&#9724;</span> <span style=\"color:#A569BD\">&#9724;</span>", "name": 3810, "id": 8, "children": [{"orbit": 8, "Type": 44, "deg": "7", "tup": [35, 53, 181, 194, 493], "str_rep": "1 2 2 3 4\n 1 2 2 3 4\n 1 2 5 3 4\n 1 1 5 3 4\n 5 5 5 3 4", "html_rep": "<span style=\"color:#73C6B6\">&#9724;</span> <span style=\"color:#F4D03F\">&#9724;</span> <span style=\"color:#F4D03F\">&#9724;</span> <span style=\"color:#CD6155\">&#9724;</span> <span style=\"color:#A569BD\">&#9724;</span><br/> <span style=\"color:#73C6B6\">&#9724;</span> <span style=\"color:#F4D03F\">&#9724;</span> <span style=\"color:#F4D03F\">&#9724;</span> <span style=\"color:#CD6155\">&#9724;</span> <span style=\"color:#A569BD\">&#9724;</span><br/> <span style=\"color:#73C6B6\">&#9724;</span> <span style=\"color:#F4D03F\">&#9724;</span> <span style=\"color:#4682B4\">&#9724;</span> <span style=\"color:#CD6155\">&#9724;</span> <span style=\"color:#A569BD\">&#9724;</span><br/> <span style=\"color:#73C6B6\">&#9724;</span> <span style=\"color:#73C6B6\">&#9724;</span> <span style=\"color:#4682B4\">&#9724;</span> <span style=\"color:#CD6155\">&#9724;</span> <span style=\"color:#A569BD\">&#9724;</span><br/> <span style=\"color:#4682B4\">&#9724;</span> <span style=\"color:#4682B4\">&#9724;</span> <span style=\"color:#4682B4\">&#9724;</span> <span style=\"color:#CD6155\">&#9724;</span> <span style=\"color:#A569BD\">&#9724;</span>", "name": 3070, "id": 38}]}]}