{"directed": false, "multigraph": false, "graph": {}, "nodes": [{"orbit": 8, "Type": 139, "deg": "9", "tup": [5, 146, 400, 461, 547], "str_rep": "1 1 1 2 2\n 1 1 2 2 2\n 3 3 4 4 4\n 3 5 5 5 4\n 3 3 5 5 4", "html_rep": "<span style=\"color:#73C6B6\">&#9724;</span> <span style=\"color:#73C6B6\">&#9724;</span> <span style=\"color:#73C6B6\">&#9724;</span> <span style=\"color:#F4D03F\">&#9724;</span> <span style=\"color:#F4D03F\">&#9724;</span><br/> <span style=\"color:#73C6B6\">&#9724;</span> <span style=\"color:#73C6B6\">&#9724;</span> <span style=\"color:#F4D03F\">&#9724;</span> <span style=\"color:#F4D03F\">&#9724;</span> <span style=\"color:#F4D03F\">&#9724;</span><br/> <span style=\"color:#CD6155\">&#9724;</span> <span style=\"color:#CD6155\">&#9724;</span> <span style=\"color:#A569BD\">&#9724;</span> <span style=\"color:#A569BD\">&#9724;</span> <span style=\"color:#A569BD\">&#9724;</span><br/> <span style=\"color:#CD6155\">&#9724;</span> <span style=\"color:#4682B4\">&#9724;</span> <span style=\"color:#4682B4\">&#9724;</span> <span style=\"color:#4682B4\">&#9724;</span> <span style=\"color:#A569BD\">&#9724;</span><br/> <span style=\"color:#CD6155\">&#9724;</span> <span style=\"color:#CD6155\">&#9724;</span> <span style=\"color:#4682B4\">&#9724;</span> <span style=\"color:#4682B4\">&#9724;</span> <span style=\"color:#A569BD\">&#9724;</span>", "name": 1632, "id": 0}, {"orbit": 8, "Type": 181, "deg": "5", "tup": [5, 147, 380, 413, 449], "str_rep": "1 1 1 2 2\n 1 1 2 2 3\n 4 5 2 3 3\n 4 5 5 5 3\n 4 4 4 5 3", "html_rep": "<span style=\"color:#73C6B6\">&#9724;</span> <span style=\"color:#73C6B6\">&#9724;</span> <span style=\"color:#73C6B6\">&#9724;</span> <span style=\"color:#F4D03F\">&#9724;</span> <span style=\"color:#F4D03F\">&#9724;</span><br/> <span style=\"color:#73C6B6\">&#9724;</span> <span style=\"color:#73C6B6\">&#9724;</span> <span style=\"color:#F4D03F\">&#9724;</span> <span style=\"color:#F4D03F\">&#9724;</span> <span style=\"color:#CD6155\">&#9724;</span><br/> <span style=\"color:#A569BD\">&#9724;</span> <span style=\"color:#4682B4\">&#9724;</span> <span style=\"color:#F4D03F\">&#9724;</span> <span style=\"color:#CD6155\">&#9724;</span> <span style=\"color:#CD6155\">&#9724;</span><br/> <span style=\"color:#A569BD\">&#9724;</span> <span style=\"color:#4682B4\">&#9724;</span> <span style=\"color:#4682B4\">&#9724;</span> <span style=\"color:#4682B4\">&#9724;</span> <span style=\"color:#CD6155\">&#9724;</span><br/> <span style=\"color:#A569BD\">&#9724;</span> <span style=\"color:#A569BD\">&#9724;</span> <span style=\"color:#A569BD\">&#9724;</span> <span style=\"color:#4682B4\">&#9724;</span> <span style=\"color:#CD6155\">&#9724;</span>", "name": 2082, "id": 1}, {"orbit": 8, "Type": 432, "deg": "7", "tup": [9, 147, 230, 380, 547], "str_rep": "1 1 1 2 2\n 3 1 2 2 4\n 3 1 2 4 4\n 3 5 5 5 4\n 3 3 5 5 4", "html_rep": "<span style=\"color:#73C6B6\">&#9724;</span> <span style=\"color:#73C6B6\">&#9724;</span> <span style=\"color:#73C6B6\">&#9724;</span> <span style=\"color:#F4D03F\">&#9724;</span> <span style=\"color:#F4D03F\">&#9724;</span><br/> <span style=\"color:#CD6155\">&#9724;</span> <span style=\"color:#73C6B6\">&#9724;</span> <span style=\"color:#F4D03F\">&#9724;</span> <span style=\"color:#F4D03F\">&#9724;</span> <span style=\"color:#A569BD\">&#9724;</span><br/> <span style=\"color:#CD6155\">&#9724;</span> <span style=\"color:#73C6B6\">&#9724;</span> <span style=\"color:#F4D03F\">&#9724;</span> <span style=\"color:#A569BD\">&#9724;</span> <span style=\"color:#A569BD\">&#9724;</span><br/> <span style=\"color:#CD6155\">&#9724;</span> <span style=\"color:#4682B4\">&#9724;</span> <span style=\"color:#4682B4\">&#9724;</span> <span style=\"color:#4682B4\">&#9724;</span> <span style=\"color:#A569BD\">&#9724;</span><br/> <span style=\"color:#CD6155\">&#9724;</span> <span style=\"color:#CD6155\">&#9724;</span> <span style=\"color:#4682B4\">&#9724;</span> <span style=\"color:#4682B4\">&#9724;</span> <span style=\"color:#A569BD\">&#9724;</span>", "name": 2793, "id": 2}, {"orbit": 8, "Type": 41, "deg": "8", "tup": [5, 165, 194, 400, 547], "str_rep": "1 1 1 2 3\n 1 1 2 2 3\n 4 4 2 2 3\n 4 5 5 5 3\n 4 4 5 5 3", "html_rep": "<span style=\"color:#73C6B6\">&#9724;</span> <span style=\"color:#73C6B6\">&#9724;</span> <span style=\"color:#73C6B6\">&#9724;</span> <span style=\"color:#F4D03F\">&#9724;</span> <span style=\"color:#CD6155\">&#9724;</span><br/> <span style=\"color:#73C6B6\">&#9724;</span> <span style=\"color:#73C6B6\">&#9724;</span> <span style=\"color:#F4D03F\">&#9724;</span> <span style=\"color:#F4D03F\">&#9724;</span> <span style=\"color:#CD6155\">&#9724;</span><br/> <span style=\"color:#A569BD\">&#9724;</span> <span style=\"color:#A569BD\">&#9724;</span> <span style=\"color:#F4D03F\">&#9724;</span> <span style=\"color:#F4D03F\">&#9724;</span> <span style=\"color:#CD6155\">&#9724;</span><br/> <span style=\"color:#A569BD\">&#9724;</span> <span style=\"color:#4682B4\">&#9724;</span> <span style=\"color:#4682B4\">&#9724;</span> <span style=\"color:#4682B4\">&#9724;</span> <span style=\"color:#CD6155\">&#9724;</span><br/> <span style=\"color:#A569BD\">&#9724;</span> <span style=\"color:#A569BD\">&#9724;</span> <span style=\"color:#4682B4\">&#9724;</span> <span style=\"color:#4682B4\">&#9724;</span> <span style=\"color:#CD6155\">&#9724;</span>", "name": 43, "id": 3}, {"orbit": 8, "Type": 509, "deg": "8", "tup": [5, 147, 380, 398, 560], "str_rep": "1 1 1 2 2\n 1 1 2 2 3\n 4 4 2 3 3\n 4 4 5 5 3\n 4 5 5 5 3", "html_rep": "<span style=\"color:#73C6B6\">&#9724;</span> <span style=\"color:#73C6B6\">&#9724;</span> <span style=\"color:#73C6B6\">&#9724;</span> <span style=\"color:#F4D03F\">&#9724;</span> <span style=\"color:#F4D03F\">&#9724;</span><br/> <span style=\"color:#73C6B6\">&#9724;</span> <span style=\"color:#73C6B6\">&#9724;</span> <span style=\"color:#F4D03F\">&#9724;</span> <span style=\"color:#F4D03F\">&#9724;</span> <span style=\"color:#CD6155\">&#9724;</span><br/> <span style=\"color:#A569BD\">&#9724;</span> <span style=\"color:#A569BD\">&#9724;</span> <span style=\"color:#F4D03F\">&#9724;</span> <span style=\"color:#CD6155\">&#9724;</span> <span style=\"color:#CD6155\">&#9724;</span><br/> <span style=\"color:#A569BD\">&#9724;</span> <span style=\"color:#A569BD\">&#9724;</span> <span style=\"color:#4682B4\">&#9724;</span> <span style=\"color:#4682B4\">&#9724;</span> <span style=\"color:#CD6155\">&#9724;</span><br/> <span style=\"color:#A569BD\">&#9724;</span> <span style=\"color:#4682B4\">&#9724;</span> <span style=\"color:#4682B4\">&#9724;</span> <span style=\"color:#4682B4\">&#9724;</span> <span style=\"color:#CD6155\">&#9724;</span>", "name": 1997, "id": 4}, {"orbit": 8, "Type": 300, "deg": "5", "tup": [5, 147, 378, 400, 551], "str_rep": "1 1 1 2 2\n 1 1 2 2 3\n 4 4 2 3 3\n 4 5 5 3 3\n 4 4 5 5 5", "html_rep": "<span style=\"color:#73C6B6\">&#9724;</span> <span style=\"color:#73C6B6\">&#9724;</span> <span style=\"color:#73C6B6\">&#9724;</span> <span style=\"color:#F4D03F\">&#9724;</span> <span style=\"color:#F4D03F\">&#9724;</span><br/> <span style=\"color:#73C6B6\">&#9724;</span> <span style=\"color:#73C6B6\">&#9724;</span> <span style=\"color:#F4D03F\">&#9724;</span> <span style=\"color:#F4D03F\">&#9724;</span> <span style=\"color:#CD6155\">&#9724;</span><br/> <span style=\"color:#A569BD\">&#9724;</span> <span style=\"color:#A569BD\">&#9724;</span> <span style=\"color:#F4D03F\">&#9724;</span> <span style=\"color:#CD6155\">&#9724;</span> <span style=\"color:#CD6155\">&#9724;</span><br/> <span style=\"color:#A569BD\">&#9724;</span> <span style=\"color:#4682B4\">&#9724;</span> <span style=\"color:#4682B4\">&#9724;</span> <span style=\"color:#CD6155\">&#9724;</span> <span style=\"color:#CD6155\">&#9724;</span><br/> <span style=\"color:#A569BD\">&#9724;</span> <span style=\"color:#A569BD\">&#9724;</span> <span style=\"color:#4682B4\">&#9724;</span> <span style=\"color:#4682B4\">&#9724;</span> <span style=\"color:#4682B4\">&#9724;</span>", "name": 3053, "id": 5}, {"orbit": 8, "Type": 424, "deg": "7", "tup": [5, 147, 380, 400, 547], "str_rep": "1 1 1 2 2\n 1 1 2 2 3\n 4 4 2 3 3\n 4 5 5 5 3\n 4 4 5 5 3", "html_rep": "<span style=\"color:#73C6B6\">&#9724;</span> <span style=\"color:#73C6B6\">&#9724;</span> <span style=\"color:#73C6B6\">&#9724;</span> <span style=\"color:#F4D03F\">&#9724;</span> <span style=\"color:#F4D03F\">&#9724;</span><br/> <span style=\"color:#73C6B6\">&#9724;</span> <span style=\"color:#73C6B6\">&#9724;</span> <span style=\"color:#F4D03F\">&#9724;</span> <span style=\"color:#F4D03F\">&#9724;</span> <span style=\"color:#CD6155\">&#9724;</span><br/> <span style=\"color:#A569BD\">&#9724;</span> <span style=\"color:#A569BD\">&#9724;</span> <span style=\"color:#F4D03F\">&#9724;</span> <span style=\"color:#CD6155\">&#9724;</span> <span style=\"color:#CD6155\">&#9724;</span><br/> <span style=\"color:#A569BD\">&#9724;</span> <span style=\"color:#4682B4\">&#9724;</span> <span style=\"color:#4682B4\">&#9724;</span> <span style=\"color:#4682B4\">&#9724;</span> <span style=\"color:#CD6155\">&#9724;</span><br/> <span style=\"color:#A569BD\">&#9724;</span> <span style=\"color:#A569BD\">&#9724;</span> <span style=\"color:#4682B4\">&#9724;</span> <span style=\"color:#4682B4\">&#9724;</span> <span style=\"color:#CD6155\">&#9724;</span>", "name": 2863, "id": 6}, {"orbit": 8, "Type": 5, "deg": "5", "tup": [5, 147, 384, 400, 508], "str_rep": "1 1 1 2 2\n 1 1 2 2 3\n 4 4 2 5 3\n 4 5 5 5 3\n 4 4 5 3 3", "html_rep": "<span style=\"color:#73C6B6\">&#9724;</span> <span style=\"color:#73C6B6\">&#9724;</span> <span style=\"color:#73C6B6\">&#9724;</span> <span style=\"color:#F4D03F\">&#9724;</span> <span style=\"color:#F4D03F\">&#9724;</span><br/> <span style=\"color:#73C6B6\">&#9724;</span> <span style=\"color:#73C6B6\">&#9724;</span> <span style=\"color:#F4D03F\">&#9724;</span> <span style=\"color:#F4D03F\">&#9724;</span> <span style=\"color:#CD6155\">&#9724;</span><br/> <span style=\"color:#A569BD\">&#9724;</span> <span style=\"color:#A569BD\">&#9724;</span> <span style=\"color:#F4D03F\">&#9724;</span> <span style=\"color:#4682B4\">&#9724;</span> <span style=\"color:#CD6155\">&#9724;</span><br/> <span style=\"color:#A569BD\">&#9724;</span> <span style=\"color:#4682B4\">&#9724;</span> <span style=\"color:#4682B4\">&#9724;</span> <span style=\"color:#4682B4\">&#9724;</span> <span style=\"color:#CD6155\">&#9724;</span><br/> <span style=\"color:#A569BD\">&#9724;</span> <span style=\"color:#A569BD\">&#9724;</span> <span style=\"color:#4682B4\">&#9724;</span> <span style=\"color:#CD6155\">&#9724;</span> <span style=\"color:#CD6155\">&#9724;</span>", "name": 2129, "id": 7}], "links": [{"source": 0, "target": 6}, {"source": 1, "target": 6}, {"source": 2, "target": 6}, {"source": 3, "target": 6}, {"source": 4, "target": 6}, {"source": 5, "target": 6}, {"source": 6, "target": 7}]}