{"directed": false, "multigraph": false, "graph": {}, "nodes": [{"orbit": 8, "Type": 232, "deg": "11", "tup": [3, 189, 211, 430, 519], "str_rep": "1 1 1 1 2\n 3 3 1 2 2\n 3 4 4 5 2\n 3 4 4 5 2\n 3 4 5 5 5", "html_rep": "<span style=\"color:#73C6B6\">&#9724;</span> <span style=\"color:#73C6B6\">&#9724;</span> <span style=\"color:#73C6B6\">&#9724;</span> <span style=\"color:#73C6B6\">&#9724;</span> <span style=\"color:#F4D03F\">&#9724;</span><br/> <span style=\"color:#CD6155\">&#9724;</span> <span style=\"color:#CD6155\">&#9724;</span> <span style=\"color:#73C6B6\">&#9724;</span> <span style=\"color:#F4D03F\">&#9724;</span> <span style=\"color:#F4D03F\">&#9724;</span><br/> <span style=\"color:#CD6155\">&#9724;</span> <span style=\"color:#A569BD\">&#9724;</span> <span style=\"color:#A569BD\">&#9724;</span> <span style=\"color:#4682B4\">&#9724;</span> <span style=\"color:#F4D03F\">&#9724;</span><br/> <span style=\"color:#CD6155\">&#9724;</span> <span style=\"color:#A569BD\">&#9724;</span> <span style=\"color:#A569BD\">&#9724;</span> <span style=\"color:#4682B4\">&#9724;</span> <span style=\"color:#F4D03F\">&#9724;</span><br/> <span style=\"color:#CD6155\">&#9724;</span> <span style=\"color:#A569BD\">&#9724;</span> <span style=\"color:#4682B4\">&#9724;</span> <span style=\"color:#4682B4\">&#9724;</span> <span style=\"color:#4682B4\">&#9724;</span>", "name": 452, "id": 0}, {"orbit": 8, "Type": 400, "deg": "8", "tup": [0, 211, 290, 451, 474], "str_rep": "1 1 1 1 1\n 2 2 3 3 3\n 2 4 5 5 3\n 2 4 4 5 3\n 2 4 4 5 5", "html_rep": "<span style=\"color:#73C6B6\">&#9724;</span> <span style=\"color:#73C6B6\">&#9724;</span> <span style=\"color:#73C6B6\">&#9724;</span> <span style=\"color:#73C6B6\">&#9724;</span> <span style=\"color:#73C6B6\">&#9724;</span><br/> <span style=\"color:#F4D03F\">&#9724;</span> <span style=\"color:#F4D03F\">&#9724;</span> <span style=\"color:#CD6155\">&#9724;</span> <span style=\"color:#CD6155\">&#9724;</span> <span style=\"color:#CD6155\">&#9724;</span><br/> <span style=\"color:#F4D03F\">&#9724;</span> <span style=\"color:#A569BD\">&#9724;</span> <span style=\"color:#4682B4\">&#9724;</span> <span style=\"color:#4682B4\">&#9724;</span> <span style=\"color:#CD6155\">&#9724;</span><br/> <span style=\"color:#F4D03F\">&#9724;</span> <span style=\"color:#A569BD\">&#9724;</span> <span style=\"color:#A569BD\">&#9724;</span> <span style=\"color:#4682B4\">&#9724;</span> <span style=\"color:#CD6155\">&#9724;</span><br/> <span style=\"color:#F4D03F\">&#9724;</span> <span style=\"color:#A569BD\">&#9724;</span> <span style=\"color:#A569BD\">&#9724;</span> <span style=\"color:#4682B4\">&#9724;</span> <span style=\"color:#4682B4\">&#9724;</span>", "name": 3151, "id": 1}, {"orbit": 8, "Type": 127, "deg": "6", "tup": [3, 189, 230, 281, 474], "str_rep": "1 1 1 1 2\n 3 4 1 2 2\n 3 4 5 5 2\n 3 4 4 5 2\n 3 3 4 5 5", "html_rep": "<span style=\"color:#73C6B6\">&#9724;</span> <span style=\"color:#73C6B6\">&#9724;</span> <span style=\"color:#73C6B6\">&#9724;</span> <span style=\"color:#73C6B6\">&#9724;</span> <span style=\"color:#F4D03F\">&#9724;</span><br/> <span style=\"color:#CD6155\">&#9724;</span> <span style=\"color:#A569BD\">&#9724;</span> <span style=\"color:#73C6B6\">&#9724;</span> <span style=\"color:#F4D03F\">&#9724;</span> <span style=\"color:#F4D03F\">&#9724;</span><br/> <span style=\"color:#CD6155\">&#9724;</span> <span style=\"color:#A569BD\">&#9724;</span> <span style=\"color:#4682B4\">&#9724;</span> <span style=\"color:#4682B4\">&#9724;</span> <span style=\"color:#F4D03F\">&#9724;</span><br/> <span style=\"color:#CD6155\">&#9724;</span> <span style=\"color:#A569BD\">&#9724;</span> <span style=\"color:#A569BD\">&#9724;</span> <span style=\"color:#4682B4\">&#9724;</span> <span style=\"color:#F4D03F\">&#9724;</span><br/> <span style=\"color:#CD6155\">&#9724;</span> <span style=\"color:#CD6155\">&#9724;</span> <span style=\"color:#A569BD\">&#9724;</span> <span style=\"color:#4682B4\">&#9724;</span> <span style=\"color:#4682B4\">&#9724;</span>", "name": 1970, "id": 2}, {"orbit": 8, "Type": 404, "deg": "8", "tup": [3, 189, 208, 474, 549], "str_rep": "1 1 1 1 2\n 3 3 1 2 2\n 3 3 4 4 2\n 3 5 5 4 2\n 5 5 5 4 4", "html_rep": "<span style=\"color:#73C6B6\">&#9724;</span> <span style=\"color:#73C6B6\">&#9724;</span> <span style=\"color:#73C6B6\">&#9724;</span> <span style=\"color:#73C6B6\">&#9724;</span> <span style=\"color:#F4D03F\">&#9724;</span><br/> <span style=\"color:#CD6155\">&#9724;</span> <span style=\"color:#CD6155\">&#9724;</span> <span style=\"color:#73C6B6\">&#9724;</span> <span style=\"color:#F4D03F\">&#9724;</span> <span style=\"color:#F4D03F\">&#9724;</span><br/> <span style=\"color:#CD6155\">&#9724;</span> <span style=\"color:#CD6155\">&#9724;</span> <span style=\"color:#A569BD\">&#9724;</span> <span style=\"color:#A569BD\">&#9724;</span> <span style=\"color:#F4D03F\">&#9724;</span><br/> <span style=\"color:#CD6155\">&#9724;</span> <span style=\"color:#4682B4\">&#9724;</span> <span style=\"color:#4682B4\">&#9724;</span> <span style=\"color:#A569BD\">&#9724;</span> <span style=\"color:#F4D03F\">&#9724;</span><br/> <span style=\"color:#4682B4\">&#9724;</span> <span style=\"color:#4682B4\">&#9724;</span> <span style=\"color:#4682B4\">&#9724;</span> <span style=\"color:#A569BD\">&#9724;</span> <span style=\"color:#A569BD\">&#9724;</span>", "name": 3892, "id": 3}, {"orbit": 8, "Type": 393, "deg": "8", "tup": [3, 189, 211, 433, 515], "str_rep": "1 1 1 1 2\n 3 3 1 2 2\n 3 4 4 5 2\n 3 4 5 5 2\n 3 4 4 5 5", "html_rep": "<span style=\"color:#73C6B6\">&#9724;</span> <span style=\"color:#73C6B6\">&#9724;</span> <span style=\"color:#73C6B6\">&#9724;</span> <span style=\"color:#73C6B6\">&#9724;</span> <span style=\"color:#F4D03F\">&#9724;</span><br/> <span style=\"color:#CD6155\">&#9724;</span> <span style=\"color:#CD6155\">&#9724;</span> <span style=\"color:#73C6B6\">&#9724;</span> <span style=\"color:#F4D03F\">&#9724;</span> <span style=\"color:#F4D03F\">&#9724;</span><br/> <span style=\"color:#CD6155\">&#9724;</span> <span style=\"color:#A569BD\">&#9724;</span> <span style=\"color:#A569BD\">&#9724;</span> <span style=\"color:#4682B4\">&#9724;</span> <span style=\"color:#F4D03F\">&#9724;</span><br/> <span style=\"color:#CD6155\">&#9724;</span> <span style=\"color:#A569BD\">&#9724;</span> <span style=\"color:#4682B4\">&#9724;</span> <span style=\"color:#4682B4\">&#9724;</span> <span style=\"color:#F4D03F\">&#9724;</span><br/> <span style=\"color:#CD6155\">&#9724;</span> <span style=\"color:#A569BD\">&#9724;</span> <span style=\"color:#A569BD\">&#9724;</span> <span style=\"color:#4682B4\">&#9724;</span> <span style=\"color:#4682B4\">&#9724;</span>", "name": 727, "id": 4}, {"orbit": 8, "Type": 493, "deg": "7", "tup": [36, 42, 189, 451, 474], "str_rep": "1 2 2 2 3\n 1 2 2 3 3\n 1 4 5 5 3\n 1 4 4 5 3\n 1 4 4 5 5", "html_rep": "<span style=\"color:#73C6B6\">&#9724;</span> <span style=\"color:#F4D03F\">&#9724;</span> <span style=\"color:#F4D03F\">&#9724;</span> <span style=\"color:#F4D03F\">&#9724;</span> <span style=\"color:#CD6155\">&#9724;</span><br/> <span style=\"color:#73C6B6\">&#9724;</span> <span style=\"color:#F4D03F\">&#9724;</span> <span style=\"color:#F4D03F\">&#9724;</span> <span style=\"color:#CD6155\">&#9724;</span> <span style=\"color:#CD6155\">&#9724;</span><br/> <span style=\"color:#73C6B6\">&#9724;</span> <span style=\"color:#A569BD\">&#9724;</span> <span style=\"color:#4682B4\">&#9724;</span> <span style=\"color:#4682B4\">&#9724;</span> <span style=\"color:#CD6155\">&#9724;</span><br/> <span style=\"color:#73C6B6\">&#9724;</span> <span style=\"color:#A569BD\">&#9724;</span> <span style=\"color:#A569BD\">&#9724;</span> <span style=\"color:#4682B4\">&#9724;</span> <span style=\"color:#CD6155\">&#9724;</span><br/> <span style=\"color:#73C6B6\">&#9724;</span> <span style=\"color:#A569BD\">&#9724;</span> <span style=\"color:#A569BD\">&#9724;</span> <span style=\"color:#4682B4\">&#9724;</span> <span style=\"color:#4682B4\">&#9724;</span>", "name": 3289, "id": 5}, {"orbit": 8, "Type": 438, "deg": "8", "tup": [3, 189, 211, 451, 474], "str_rep": "1 1 1 1 2\n 3 3 1 2 2\n 3 4 5 5 2\n 3 4 4 5 2\n 3 4 4 5 5", "html_rep": "<span style=\"color:#73C6B6\">&#9724;</span> <span style=\"color:#73C6B6\">&#9724;</span> <span style=\"color:#73C6B6\">&#9724;</span> <span style=\"color:#73C6B6\">&#9724;</span> <span style=\"color:#F4D03F\">&#9724;</span><br/> <span style=\"color:#CD6155\">&#9724;</span> <span style=\"color:#CD6155\">&#9724;</span> <span style=\"color:#73C6B6\">&#9724;</span> <span style=\"color:#F4D03F\">&#9724;</span> <span style=\"color:#F4D03F\">&#9724;</span><br/> <span style=\"color:#CD6155\">&#9724;</span> <span style=\"color:#A569BD\">&#9724;</span> <span style=\"color:#4682B4\">&#9724;</span> <span style=\"color:#4682B4\">&#9724;</span> <span style=\"color:#F4D03F\">&#9724;</span><br/> <span style=\"color:#CD6155\">&#9724;</span> <span style=\"color:#A569BD\">&#9724;</span> <span style=\"color:#A569BD\">&#9724;</span> <span style=\"color:#4682B4\">&#9724;</span> <span style=\"color:#F4D03F\">&#9724;</span><br/> <span style=\"color:#CD6155\">&#9724;</span> <span style=\"color:#A569BD\">&#9724;</span> <span style=\"color:#A569BD\">&#9724;</span> <span style=\"color:#4682B4\">&#9724;</span> <span style=\"color:#4682B4\">&#9724;</span>", "name": 890, "id": 6}, {"orbit": 8, "Type": 343, "deg": "10", "tup": [3, 194, 211, 360, 451], "str_rep": "1 1 1 1 2\n 3 3 1 4 2\n 3 5 4 4 2\n 3 5 5 4 2\n 3 5 5 4 2", "html_rep": "<span style=\"color:#73C6B6\">&#9724;</span> <span style=\"color:#73C6B6\">&#9724;</span> <span style=\"color:#73C6B6\">&#9724;</span> <span style=\"color:#73C6B6\">&#9724;</span> <span style=\"color:#F4D03F\">&#9724;</span><br/> <span style=\"color:#CD6155\">&#9724;</span> <span style=\"color:#CD6155\">&#9724;</span> <span style=\"color:#73C6B6\">&#9724;</span> <span style=\"color:#A569BD\">&#9724;</span> <span style=\"color:#F4D03F\">&#9724;</span><br/> <span style=\"color:#CD6155\">&#9724;</span> <span style=\"color:#4682B4\">&#9724;</span> <span style=\"color:#A569BD\">&#9724;</span> <span style=\"color:#A569BD\">&#9724;</span> <span style=\"color:#F4D03F\">&#9724;</span><br/> <span style=\"color:#CD6155\">&#9724;</span> <span style=\"color:#4682B4\">&#9724;</span> <span style=\"color:#4682B4\">&#9724;</span> <span style=\"color:#A569BD\">&#9724;</span> <span style=\"color:#F4D03F\">&#9724;</span><br/> <span style=\"color:#CD6155\">&#9724;</span> <span style=\"color:#4682B4\">&#9724;</span> <span style=\"color:#4682B4\">&#9724;</span> <span style=\"color:#A569BD\">&#9724;</span> <span style=\"color:#F4D03F\">&#9724;</span>", "name": 540, "id": 7}, {"orbit": 8, "Type": 245, "deg": "7", "tup": [10, 155, 211, 451, 474], "str_rep": "1 1 1 2 2\n 3 3 1 1 2\n 3 4 5 5 2\n 3 4 4 5 2\n 3 4 4 5 5", "html_rep": "<span style=\"color:#73C6B6\">&#9724;</span> <span style=\"color:#73C6B6\">&#9724;</span> <span style=\"color:#73C6B6\">&#9724;</span> <span style=\"color:#F4D03F\">&#9724;</span> <span style=\"color:#F4D03F\">&#9724;</span><br/> <span style=\"color:#CD6155\">&#9724;</span> <span style=\"color:#CD6155\">&#9724;</span> <span style=\"color:#73C6B6\">&#9724;</span> <span style=\"color:#73C6B6\">&#9724;</span> <span style=\"color:#F4D03F\">&#9724;</span><br/> <span style=\"color:#CD6155\">&#9724;</span> <span style=\"color:#A569BD\">&#9724;</span> <span style=\"color:#4682B4\">&#9724;</span> <span style=\"color:#4682B4\">&#9724;</span> <span style=\"color:#F4D03F\">&#9724;</span><br/> <span style=\"color:#CD6155\">&#9724;</span> <span style=\"color:#A569BD\">&#9724;</span> <span style=\"color:#A569BD\">&#9724;</span> <span style=\"color:#4682B4\">&#9724;</span> <span style=\"color:#F4D03F\">&#9724;</span><br/> <span style=\"color:#CD6155\">&#9724;</span> <span style=\"color:#A569BD\">&#9724;</span> <span style=\"color:#A569BD\">&#9724;</span> <span style=\"color:#4682B4\">&#9724;</span> <span style=\"color:#4682B4\">&#9724;</span>", "name": 637, "id": 8}], "links": [{"source": 0, "target": 4}, {"source": 0, "target": 6}, {"source": 1, "target": 6}, {"source": 2, "target": 6}, {"source": 3, "target": 6}, {"source": 4, "target": 6}, {"source": 5, "target": 6}, {"source": 6, "target": 7}, {"source": 6, "target": 8}]}